backend/Dockerfile
backend/README.md
backend/setup.cfg
backend/setup.py
backend/app/config.py
backend/app/main.py
backend/app/models.py
backend/app/api/deps.py
backend/app/api/api_v1/endpoints/admin.py
backend/app/api/api_v1/endpoints/prompt_tune.py
backend/app/api/api_v1/endpoints/query.py
backend/app/api/api_v1/endpoints/question_gen.py
backend/app/api/api_v1/endpoints/search.py
backend/app/api/v1/endpoints.py
backend/app/core/config.py
backend/app/core/errors.py
backend/app/core/logging.py
backend/app/db/base.py
backend/app/db/init_db.py
backend/app/db/session.py
backend/app/middleware/auth.py
backend/app/middleware/error_handler.py
backend/app/middleware/logging.py
backend/app/middleware/rate_limiter.py
backend/app/middleware/request_handler.py
backend/app/middleware/request_logger.py
backend/app/schemas/search.py
backend/app/services/graph.py
backend/app/services/graph_service.py
backend/app/services/indexer.py
backend/app/services/llm.py
backend/app/services/prompt_tune.py
backend/app/services/query.py
backend/app/services/question_generator.py
backend/app/services/search.py
backend/app/services/search_engine.py
backend/app/utils/cache.py
backend/app/utils/context_builder.py
backend/app/utils/data_processing.py
backend/app/utils/logging.py
backend/src/graphfleet/__init__.py
backend/src/graphfleet/app/__init__.py
backend/src/graphfleet/app/models.py
backend/src/graphfleet/app/services.py
backend/src/graphfleet/core/__init__.py
backend/src/graphfleet/core/features.py
backend/src/graphfleet/core/storage.py
backend/src/graphfleet/core/types.py
backend/templates/base.yml
backend/templates/settings.yml
backend/tests/conftest.py
backend/tests/test_api.py
backend/tests/test_search_engine.py
graphfleet-0.7.5.dist-info/METADATA
graphfleet-0.7.5.dist-info/WHEEL
graphfleet-0.7.5.dist-info/licenses/LICENSE
graphfleet-0.7.5.dist-info/RECORD
