Metadata-Version: 2.4
Name: graphfleet
Version: 0.7.5
Summary: A graph-based knowledge management and query system
Author-email: Zachary BENSALEM <contact@qreddence.ai>
License-Expression: MIT
License-File: LICENSE
Keywords: graph,knowledge,search,semantic
Classifier: Development Status :: 4 - Beta
Classifier: Intended Audience :: Developers
Classifier: License :: OSI Approved :: MIT License
Classifier: Programming Language :: Python :: 3
Classifier: Programming Language :: Python :: 3.10
Classifier: Programming Language :: Python :: 3.11
Classifier: Topic :: Software Development :: Libraries :: Python Modules
Requires-Python: >=3.10
Requires-Dist: faiss-cpu>=1.7.4
Requires-Dist: fastapi>=0.100.0
Requires-Dist: ipykernel>=6.0.0
Requires-Dist: jupyter>=1.0.0
Requires-Dist: networkx>=3.4.2
Requires-Dist: notebook>=7.0.0
Requires-Dist: numpy>=1.24.0
Requires-Dist: pandas>=2.0.0
Requires-Dist: pydantic>=2.0.0
Requires-Dist: pyyaml>=6.0
Requires-Dist: scikit-learn>=1.3.0
Requires-Dist: sentence-transformers>=2.2.2
Requires-Dist: uvicorn>=0.22.0
Provides-Extra: dev
Requires-Dist: black>=23.0.0; extra == 'dev'
Requires-Dist: isort>=5.12.0; extra == 'dev'
Requires-Dist: jupyterlab>=4.0.0; extra == 'dev'
Requires-Dist: mypy>=1.0.0; extra == 'dev'
Requires-Dist: nbconvert>=7.0.0; extra == 'dev'
Requires-Dist: nbformat>=5.0.0; extra == 'dev'
Requires-Dist: pytest-asyncio>=0.21.0; extra == 'dev'
Requires-Dist: pytest>=7.0.0; extra == 'dev'
Requires-Dist: ruff>=0.1.0; extra == 'dev'
Requires-Dist: types-networkx>=3.4.2; extra == 'dev'
